{
  "version": "6",
  "dialect": "postgresql",
  "entries": [
    {
      "idx": 0,
      "version": "6",
      "when": 1779810838791,
      "tag": "0000_worthless_leper_queen",
      "breakpoints": true
    },
    {
      "idx": 1,
      "version": "6",
      "when": 1779810838792,
      "tag": "0001_add_must_change_password",
      "breakpoints": true
    },
    {
      "idx": 2,
      "version": "6",
      "when": 1779810838793,
      "tag": "0002_add_message_fields",
      "breakpoints": true
    },
    {
      "idx": 3,
      "version": "6",
      "when": 1779810838794,
      "tag": "0003_audit_push_resets_newsletter",
      "breakpoints": true
    },
    {
      "idx": 4,
      "version": "6",
      "when": 1779810838795,
      "tag": "0004_orders",
      "breakpoints": true
    },
    {
      "idx": 5,
      "version": "6",
      "when": 1748332800000,
      "tag": "0005_product_categories",
      "breakpoints": true
    }
  ]
}
